deepshm/__init__.py
deepshm/example.py
deepshm/functions.py
deepshm-0.0.1.dist-info/LICENSE
deepshm-0.0.1.dist-info/METADATA
deepshm-0.0.1.dist-info/WHEEL
deepshm-0.0.1.dist-info/top_level.txt
deepshm-0.0.1.dist-info/RECORD
