Metadata-Version: 2.1
Name: deepshm
Version: 0.0.1
Summary: A package for training and applying neural networks aimed to deal with genomic data
Home-page: https://gitlab.com/maccarthyslab/deepshm
Author: akrantsevich
Author-email: akrantsevich@gmail.com
License: UNKNOWN
Platform: UNKNOWN
Classifier: Programming Language :: Python :: 3
Classifier: License :: OSI Approved :: MIT License
Classifier: Operating System :: OS Independent
Requires-Python: >=3.6
License-File: LICENSE
